odoo/addons/l10n_ro_account_period_close/README.rst
odoo/addons/l10n_ro_account_period_close/__init__.py
odoo/addons/l10n_ro_account_period_close/__manifest__.py
odoo/addons/l10n_ro_account_period_close/i18n/l10n_ro_account_period_close.pot
odoo/addons/l10n_ro_account_period_close/i18n/ro.po
odoo/addons/l10n_ro_account_period_close/migrations/14.0.2.2.1/pre-migration.py
odoo/addons/l10n_ro_account_period_close/models/__init__.py
odoo/addons/l10n_ro_account_period_close/models/account.py
odoo/addons/l10n_ro_account_period_close/models/account_period_close.py
odoo/addons/l10n_ro_account_period_close/readme/CONFIGURE.rst
odoo/addons/l10n_ro_account_period_close/readme/CONTRIBUTORS.rst
odoo/addons/l10n_ro_account_period_close/readme/DESCRIPTION.rst
odoo/addons/l10n_ro_account_period_close/readme/INSTALL.rst
odoo/addons/l10n_ro_account_period_close/readme/USAGE.rst
odoo/addons/l10n_ro_account_period_close/security/account_security.xml
odoo/addons/l10n_ro_account_period_close/security/ir.model.access.csv
odoo/addons/l10n_ro_account_period_close/static/description/icon.png
odoo/addons/l10n_ro_account_period_close/static/description/index.html
odoo/addons/l10n_ro_account_period_close/tests/__init__.py
odoo/addons/l10n_ro_account_period_close/tests/test_period_closing.py
odoo/addons/l10n_ro_account_period_close/views/account_period_close_view.xml
odoo/addons/l10n_ro_account_period_close/wizards/__init__.py
odoo/addons/l10n_ro_account_period_close/wizards/wizard_account_period_closing.py
odoo/addons/l10n_ro_account_period_close/wizards/wizard_account_period_closing_view.xml
odoo14_addon_l10n_ro_account_period_close-14.0.3.6.0.dist-info/METADATA
odoo14_addon_l10n_ro_account_period_close-14.0.3.6.0.dist-info/WHEEL
odoo14_addon_l10n_ro_account_period_close-14.0.3.6.0.dist-info/top_level.txt
odoo14_addon_l10n_ro_account_period_close-14.0.3.6.0.dist-info/RECORD
